{
  "employee": [
    {
      "firstname": "rameshxxx",
      "lastname": "aaxaA",
      "phoneno": 1234567898,
      "email": "amresh1098@gmail.com",
      "id": 6
    },
    {
      "firstname": "ddd",
      "lastname": "aaxaA",
      "phoneno": 1234567898,
      "email": "amresh1098@gmail.com",
      "id": 7
    },
    {
      "firstname": "cdcdcd",
      "lastname": "aaxaA",
      "phoneno": 1234567898,
      "email": "amresh1098@gmail.com",
      "id": 8
    },
    {
      "firstname": "ddd",
      "lastname": "aaxaA",
      "phoneno": 1234567898,
      "email": "amresh1098@gmail.com",
      "id": 9
    },
    {
      "firstname": "ddd",
      "lastname": "aaxaA",
      "phoneno": 1234567898,
      "email": "amresh1098@gmail.com",
      "id": 10
    },
    {
      "firstname": "ddd",
      "lastname": "aaxaA",
      "phoneno": 1234567898,
      "email": "amresh1098@gmail.com",
      "id": 11
    },
    {
      "firstname": "ddd",
      "lastname": "aaxaA",
      "phoneno": 1234567898,
      "email": "amresh1098@gmail.com",
      "id": 12
    }
  ]
}